CHANGELOG.md
CODE_OF_CONDUCT.md
LICENSE
MANIFEST.in
PULL_REQUEST_TEMPLATE.md
README.md
README.rst
entry_points.txt
local_test.txt
pyproject.toml
requirements.txt
setup.cfg
test-requirements.txt
pywebpush/__init__.py
pywebpush/__main__.py
pywebpush.egg-info/PKG-INFO
pywebpush.egg-info/SOURCES.txt
pywebpush.egg-info/dependency_links.txt
pywebpush.egg-info/entry_points.txt
pywebpush.egg-info/requires.txt
pywebpush.egg-info/top_level.txt
pywebpush/tests/__init__.py
pywebpush/tests/test_webpush.py