Metadata-Version: 2.1
Name: pywebpush
Version: 2.0.3
Summary: WebPush publication library
Author-email: JR Conlin <src+webpusher@jrconlin.com>
License: MPL-2.0
Project-URL: Homepage, https://github.com/web-push-libs/pywebpush
Keywords: webpush,vapid,notification
Classifier: Topic :: Internet :: WWW/HTTP
Classifier: Programming Language :: Python :: Implementation :: PyPy
Classifier: Programming Language :: Python
Classifier: Programming Language :: Python :: 3
Classifier: License :: OSI Approved :: Mozilla Public License 2.0 (MPL 2.0)
License-File: LICENSE
Requires-Dist: aiohttp
Requires-Dist: cryptography>=2.6.1
Requires-Dist: http-ece>=1.1.0
Requires-Dist: requests>=2.21.0
Requires-Dist: six>=1.15.0
Requires-Dist: py-vapid>=1.7.0
Provides-Extra: dev
Requires-Dist: black; extra == "dev"
Requires-Dist: mock; extra == "dev"
Requires-Dist: pytest; extra == "dev"
